magnetron/__init__.py
magnetron/_bootstrap.py
magnetron/_error.py
magnetron/_ffi_cdecl_generated.py
magnetron/_tensor.py
magnetron/context.py
magnetron/dtype.py
magnetron/libmagnetron_core.so
magnetron/libmagnetron_cpu.so
magnetron/optim.py
magnetron/nn/__init__.py
magnetron/nn/activations.py
magnetron/nn/layers.py
magnetron/nn/loss.py
magnetron/nn/module.py
magnetron.libs/libatomic-35750833.so.1.0.0
magnetron-0.1.4.dist-info/METADATA
magnetron-0.1.4.dist-info/WHEEL
magnetron-0.1.4.dist-info/RECORD
magnetron-0.1.4.dist-info/licenses/LICENSE
