Metadata-Version: 2.2
Name: magnetron
Version: 0.1.4
Summary: High-performance, lightweight deep-learning library with a PyTorch like API and GPU support.
Keywords: machine-learning,deep-learning,neural-networks,gpu,simd
Author-Email: Mario Sieg <mario.sieg.64@gmail.com>
License: Copyright 2025 Mario Sieg
Requires-Python: >=3.10
Requires-Dist: cffi
Provides-Extra: dev
Requires-Dist: ruff; extra == "dev"
Requires-Dist: torch; extra == "dev"
Requires-Dist: numpy; extra == "dev"
Requires-Dist: transformers; extra == "dev"
Requires-Dist: tiktoken; extra == "dev"
Requires-Dist: matplotlib; extra == "dev"
Requires-Dist: pytest; extra == "dev"
Requires-Dist: pytest-xdist; extra == "dev"
Requires-Dist: pyinstrument; extra == "dev"
Requires-Dist: rich; extra == "dev"
